[
  {
    "id": "1",
    "ticket": "TK-001",
    "estado": "Presupuesto",
    "cliente": "Cliente",
    "modelo": "Ender-3 V2",
    "fechaFormulario": "2025-06-01",
    "notaTecnico": "Cliente indica que la boquilla no calienta.",
    "notaAdmin": "Revisar conexión del hotend.",
    "comentarios": "Pérdida de filamento al iniciar impresión.",
    "tecnico": "Lucas P.",
    "cubreGarantia": "Sí",
    "notaInterna": "Equipo recibido sin caja original.",
    "linkPresupuesto": "https://example.com/presupuesto/1",
    "monto": "6500",
    "costoDelivery": "Envíar",
    "infoDelivery": "Retirar por sucursal Villa Crespo",
    "dniCuit": "20304567891",
    "whatsapp": "+54 11 5555-5555",
    "correo": "cliente@correo.com",
    "cobrado": "No",
    "timestampPresupuesto": "2025-06-01T10:30:00",
    "timestampListo": "2025-06-05T15:00:00",
    "imagen": "/printer-placeholder.svg"
  },
  {
    "id": "2",
    "ticket": "TK-001",
    "estado": "Presupuesto",
    "cliente": "Cliente",
    "modelo": "Ender-3 V2",
    "fechaFormulario": "2025-06-01",
    "notaTecnico": "Cliente indica que la boquilla no calienta.",
    "notaAdmin": "Revisar conexión del hotend.",
    "comentarios": "Pérdida de filamento al iniciar impresión.",
    "tecnico": "Lucas P.",
    "cubreGarantia": "Sí",
    "notaInterna": "Equipo recibido sin caja original.",
    "linkPresupuesto": "https://example.com/presupuesto/1",
    "monto": "6500",
    "costoDelivery": "Envíar",
    "infoDelivery": "Retirar por sucursal Villa Crespo",
    "dniCuit": "20304567891",
    "whatsapp": "+54 11 5555-5555",
    "correo": "cliente@correo.com",
    "cobrado": "No",
    "timestampPresupuesto": "2025-06-01T10:30:00",
    "timestampListo": "2025-06-05T15:00:00",
    "imagen": "/printer-placeholder.svg"
  },
  {
    "id": "3",
    "ticket": "TK-001",
    "estado": "Presupuesto",
    "cliente": "Cliente",
    "modelo": "Ender-3 V2",
    "fechaFormulario": "2025-06-01",
    "notaTecnico": "Cliente indica que la boquilla no calienta.",
    "notaAdmin": "Revisar conexión del hotend.",
    "comentarios": "Pérdida de filamento al iniciar impresión.",
    "tecnico": "Lucas P.",
    "cubreGarantia": "Sí",
    "notaInterna": "Equipo recibido sin caja original.",
    "linkPresupuesto": "https://example.com/presupuesto/1",
    "monto": "6500",
    "costoDelivery": "Envíar",
    "infoDelivery": "Retirar por sucursal Villa Crespo",
    "dniCuit": "20304567891",
    "whatsapp": "+54 11 5555-5555",
    "correo": "cliente@correo.com",
    "cobrado": "No",
    "timestampPresupuesto": "2025-06-01T10:30:00",
    "timestampListo": "2025-06-05T15:00:00",
    "imagen": "/printer-placeholder.svg"
  },
  {
    "id": "4",
    "ticket": "TK-001",
    "estado": "Presupuesto",
    "cliente": "Cliente",
    "modelo": "Ender-3 V2",
    "fechaFormulario": "2025-06-01",
    "notaTecnico": "Cliente indica que la boquilla no calienta.",
    "notaAdmin": "Revisar conexión del hotend.",
    "comentarios": "Pérdida de filamento al iniciar impresión.",
    "tecnico": "Lucas P.",
    "cubreGarantia": "Sí",
    "notaInterna": "Equipo recibido sin caja original.",
    "linkPresupuesto": "https://example.com/presupuesto/1",
    "monto": "6500",
    "costoDelivery": "Envíar",
    "infoDelivery": "Retirar por sucursal Villa Crespo",
    "dniCuit": "20304567891",
    "whatsapp": "+54 11 5555-5555",
    "correo": "cliente@correo.com",
    "cobrado": "No",
    "timestampPresupuesto": "2025-06-01T10:30:00",
    "timestampListo": "2025-06-05T15:00:00",
    "imagen": "/printer-placeholder.svg"
  }
]
